pydump.py
setup.py
pydump.egg-info/PKG-INFO
pydump.egg-info/SOURCES.txt
pydump.egg-info/dependency_links.txt
pydump.egg-info/entry_points.txt
pydump.egg-info/top_level.txt